splisosm/__init__.py
splisosm/dataset.py
splisosm/hyptest.py
splisosm/hyptest_glmm.py
splisosm/hyptest_np.py
splisosm/kernel.py
splisosm/likelihood.py
splisosm/logger.py
splisosm/model.py
splisosm/simulation.py
splisosm/utils.py
splisosm-1.0.2.dist-info/licenses/LICENSE
splisosm-1.0.2.dist-info/METADATA
splisosm-1.0.2.dist-info/WHEEL
splisosm-1.0.2.dist-info/top_level.txt
splisosm-1.0.2.dist-info/RECORD
