Metadata-Version: 2.4
Name: splisosm
Version: 1.0.2
Summary: Spatial isoform statistical modeling (SPLISOSM)
Author: Jiayu Su
License-Expression: BSD-3-Clause
Project-URL: repository, https://github.com/JiayuSuPKU/SPLISOSM
Requires-Python: <=4.0,>=3.9
License-File: LICENSE
Requires-Dist: numpy
Requires-Dist: pandas
Requires-Dist: torch
Requires-Dist: scipy
Requires-Dist: tqdm
Requires-Dist: smoother-omics
Provides-Extra: dev
Requires-Dist: jupyter-lab; extra == "dev"
Requires-Dist: ipykernel; extra == "dev"
Requires-Dist: ipywidgets; extra == "dev"
Requires-Dist: plotnine; extra == "dev"
Requires-Dist: scanpy; extra == "dev"
Requires-Dist: python-igraph; extra == "dev"
Requires-Dist: leidenalg; extra == "dev"
Requires-Dist: rich; extra == "dev"
Requires-Dist: pyro-ppl; extra == "dev"
Requires-Dist: scikit-bio>=0.5.9; extra == "dev"
Dynamic: license-file
